{
	"description": "项目配置文件",
	"packOptions": {
		"ignore": [
			{
				"type": "folder",
				"value": "node_modules"
			},
			{
				"type": "folder",
				"value": "dist"
			}
		]
	},
	"setting": {
		"urlCheck": false,
		"es6": true,
		"enhance": true,
		"postcss": true,
		"minified": true,
		"newFeature": true,
		"coverView": true,
		"nodeModules": true,
		"autoAudits": false,
		"checkInvalidKey": true,
		"checkSiteMap": true,
		"uploadWithSourceMap": true,
		"babelSetting": {
			"ignore": [],
			"disablePlugins": [],
			"outputPath": ""
		}
	},
	"compileType": "miniprogram",
	"libVersion": "2.10.2",
	"appid": "wx3cc8d02657120f06",
	"projectname": "minprogram-temp",
	"debugOptions": {
		"hidedInDevtools": []
	},
	"isGameTourist": false,
	"simulatorType": "wechat",
	"simulatorPluginLibVersion": {},
	"condition": {
		"search": {
			"current": -1,
			"list": []
		},
		"conversation": {
			"current": -1,
			"list": []
		},
		"plugin": {
			"current": -1,
			"list": []
		},
		"game": {
			"currentL": -1,
			"list": []
		},
		"gamePlugin": {
			"current": -1,
			"list": []
		},
		"miniprogram": {
			"current": 0,
			"list": [
				{
					"id": -1,
					"name": "receipt",
					"pathName": "pages/loading/index",
					"query": "name=test",
					"scene": 1007
				},
				{
					"id": -1,
					"name": "guide",
					"pathName": "pages/index/index",
					"query": "guideCode=13631297822",
					"scene": 1011
				}
			]
		}
	}
}